collatex_critical/__init__.py
collatex_critical/cli.py
collatex_critical/collatex_critical.py
collatex_critical/generate.py
collatex_critical/utils.py
collatex_critical/resources/fontlist.json
collatex_critical/resources/footnotes-to-titles.js
collatex_critical/resources/header.tex
collatex_critical/resources/header_script.html
collatex_critical-0.2.0.dist-info/licenses/LICENSE
collatex_critical-0.2.0.dist-info/METADATA
collatex_critical-0.2.0.dist-info/WHEEL
collatex_critical-0.2.0.dist-info/entry_points.txt
collatex_critical-0.2.0.dist-info/top_level.txt
collatex_critical-0.2.0.dist-info/RECORD
