Metadata-Version: 2.4
Name: collatex-critical
Version: 0.2.0
Summary: Critical edition enhancements for CollateX with footnote apparatus and transliterations
Home-page: https://github.com/drdhaval2785/collatex-critical
Author: Dr. Dhaval Patel
Author-email: "Dr. Dhaval Patel" <drdhaval2785@gmail.com>
License-Expression: GPL-3.0-or-later
Project-URL: Homepage, https://github.com/drdhaval2785/collatex-critical
Classifier: Programming Language :: Python :: 3
Classifier: Operating System :: OS Independent
Classifier: Topic :: Text Processing :: Linguistic
Classifier: Intended Audience :: Education
Requires-Python: >=3.8
License-File: LICENSE
Requires-Dist: indic-transliteration
Dynamic: author
Dynamic: home-page
Dynamic: license-file
Dynamic: requires-python
